setup.py
djangbone/__init__.py
djangbone/models.py
djangbone/tests.py
djangbone/views.py
djangbone.egg-info/PKG-INFO
djangbone.egg-info/SOURCES.txt
djangbone.egg-info/dependency_links.txt
djangbone.egg-info/top_level.txt