Metadata-Version: 1.0
Name: djangbone
Version: 0.0.2
Summary: Makes it easy for Django backends to talk to Backbone.js.
Home-page: https://github/af/djangbone
Author: Aaron Franks
Author-email: aaron.franks+djangbone@gmail.com
License: UNKNOWN
Keywords: django,backbone.js
Platform: UNKNOWN
Classifier: Environment :: Web Environment
Classifier: Framework :: Django
Classifier: Intended Audience :: Developers
Classifier: License :: OSI Approved :: BSD License
Classifier: Operating System :: OS Independent
Classifier: Programming Language :: Python
